COPYING
LICENSE
MANIFEST.in
README.md
pyproject.toml
setup.cfg
setup.py
pakages/__init__.py
pakages/build.py
pakages/client.py
pakages/defaults.py
pakages/logger.py
pakages/oras.py
pakages/schemas.py
pakages/settings.py
pakages/settings.yml
pakages/version.py
pakages/worker.py
pakages.egg-info/PKG-INFO
pakages.egg-info/SOURCES.txt
pakages.egg-info/dependency_links.txt
pakages.egg-info/entry_points.txt
pakages.egg-info/not-zip-safe
pakages.egg-info/requires.txt
pakages.egg-info/top_level.txt
pakages/builders/__init__.py
pakages/builders/python.py
pakages/builders/spack/__init__.py
pakages/builders/spack/cache.py
pakages/builders/spack/client.py
pakages/builders/spack/sbom.py
pakages/builders/spack/utils.py
pakages/cli/__init__.py
pakages/cli/build.py
pakages/cli/config.py
pakages/cli/helpers.py
pakages/cli/install.py
pakages/cli/shell.py
pakages/handlers/__init__.py
pakages/handlers/github.py
pakages/utils/__init__.py
pakages/utils/command.py
pakages/utils/fileio.py
pakages/utils/terminal.py