Metadata-Version: 2.1
Name: pakages
Version: 0.0.21
Summary: GitHub packages package manager.
Home-page: https://github.com/syspack/pakages
Author: Vanessa Sochat, Alec Scott
Maintainer: Vanessa Sochat, Alec Scott
License: LICENSE
Keywords: software,GitHub packages.
Platform: UNKNOWN
Classifier: Intended Audience :: Science/Research
Classifier: Intended Audience :: Developers
Classifier: License :: OSI Approved :: Apache Software License
Classifier: Programming Language :: Python
Classifier: Topic :: Software Development
Classifier: Topic :: Scientific/Engineering
Classifier: Operating System :: Unix
Classifier: Programming Language :: Python :: 3.8
Provides-Extra: all
License-File: LICENSE
License-File: COPYING
